examples/__init__.py
examples/readme_example.py
examples/strict_class_example.py
pyparcel/__init__.py
pyparcel/__version__.py
pyparcel/api.py
pyparcel/strict_type.py
pyparcel-1.0.0.dist-info/LICENSE
pyparcel-1.0.0.dist-info/METADATA
pyparcel-1.0.0.dist-info/WHEEL
pyparcel-1.0.0.dist-info/top_level.txt
pyparcel-1.0.0.dist-info/RECORD
