Metadata-Version: 2.1
Name: pyparcel
Version: 1.0.0
Summary: Easy to use binary packer that doesn't require struct's specifications
Home-page: https://github.com/najaco/pyparcel
Author: Nathan Cohen
Author-email: ncohen4299@gmail.com
License: UNKNOWN
Platform: UNKNOWN
Classifier: Programming Language :: Python :: 3
Classifier: License :: OSI Approved :: MIT License
Classifier: Operating System :: OS Independent
Requires-Python: >=3.6
